setup.cfg
setup.py
correiospy/__init__.py
correiospy/calculator.py
correiospy/config.py
correiospy/errors.py
correiospy/format_order_codes.py
correiospy/search_engine.py
correiospy/service_codes.py
correiospy/utils.py
correiospy.egg-info/PKG-INFO
correiospy.egg-info/SOURCES.txt
correiospy.egg-info/dependency_links.txt
correiospy.egg-info/pbr.json
correiospy.egg-info/top_level.txt