Metadata-Version: 1.1
Name: correiospy
Version: 1.0
Summary: Calculates the amount of supplies through zip code. The values are found at WS the Correios in Brazil.
Home-page: http://github.com/guicarvalho/correiospy
Author: Guilherme Arthur de Carvalho
Author-email: gui.ifsp11@gmail.com
License: UNKNOWN
Download-URL: https://github.com/guicarvalho/correiospy/tarball/1.0
Keywords: zip_code,correios,find zip code
Platform: UNKNOWN
